<keymap version="1" name="Default copy" parent="$default">
  <action id="ActivateCommitToolWindow" />
  <action id="ActivateSciViewToolWindow">
    <keyboard-shortcut first-keystroke="alt 0" />
  </action>
  <action id="ChangesView.Diff" />
  <action id="CompareTwoFiles" />
  <action id="Console.Execute.Multiline" />
  <action id="DebugClass">
    <keyboard-shortcut first-keystroke="shift ctrl f9" />
  </action>
  <action id="Diff.ShowDiff" />
  <action id="DirDiffMenu.SynchronizeDiff.All" />
  <action id="EditorDeleteLine">
    <keyboard-shortcut first-keystroke="ctrl d" />
  </action>
  <action id="EditorDeleteToLineEnd">
    <keyboard-shortcut first-keystroke="shift ctrl delete" />
  </action>
  <action id="EditorDeleteToLineStart">
    <keyboard-shortcut first-keystroke="shift ctrl back_space" />
  </action>
  <action id="EditorDuplicate" />
  <action id="EditorDuplicateLines">
    <keyboard-shortcut first-keystroke="ctrl alt down" />
  </action>
  <action id="EditorMoveToPageBottom" />
  <action id="EditorMoveToPageTop" />
  <action id="EditorSplitLine" />
  <action id="ExecuteInPyConsoleAction">
    <keyboard-shortcut first-keystroke="shift alt e" />
    <keyboard-shortcut first-keystroke="ctrl enter" />
  </action>
  <action id="FileChooser.GotoDesktop" />
  <action id="JumpToLastChange" />
  <action id="NextOccurence" />
  <action id="NextTab">
    <keyboard-shortcut first-keystroke="alt right" />
    <keyboard-shortcut first-keystroke="ctrl page_down" />
  </action>
  <action id="PreviousTab">
    <keyboard-shortcut first-keystroke="alt left" />
    <keyboard-shortcut first-keystroke="ctrl page_up" />
  </action>
  <action id="PyExecuteCellAction" />
  <action id="RunDashboard.CopyConfiguration" />
  <action id="SendEOF" />
  <action id="Unwrap" />
  <action id="ViewSource" />
  <action id="XDebugger.CopyWatch" />
  <action id="com.jetbrains.python.console.RunPythonOrDebugConsoleAction">
    <keyboard-shortcut first-keystroke="alt i" />
  </action>
  <action id="openAssertEqualsDiff" />
</keymap>